kb_socket/__init__.py
kb_socket/default.py
kb_socket/driver.py
kb_socket/kb_promise.py
kb_socket/kb_protocol.py
kb_socket/kb_socket.py
kb_socket/runner.py
kromblast_socket-0.3.1.dist-info/LICENSE
kromblast_socket-0.3.1.dist-info/METADATA
kromblast_socket-0.3.1.dist-info/WHEEL
kromblast_socket-0.3.1.dist-info/top_level.txt
kromblast_socket-0.3.1.dist-info/RECORD
